<?xml version="1.0" ?>
<annotation>
   <size>
      <width>1920</width>
      <height>1080</height>
      <depth>3</depth>
   </size>
   <object>
      <name>1</name>
      <difficult>0</difficult>
      <bndbox>
         <xmin>1049</xmin>
         <xmax>1155</xmax>
         <ymin>971</ymin>
         <ymax>1069</ymax>
      </bndbox>
   </object>
   <object>
      <name>1</name>
      <difficult>0</difficult>
      <bndbox>
         <xmin>249</xmin>
         <xmax>358</xmax>
         <ymin>941</ymin>
         <ymax>1045</ymax>
      </bndbox>
   </object>
   <object>
      <name>1</name>
      <difficult>0</difficult>
      <bndbox>
         <xmin>1512</xmin>
         <xmax>1606</xmax>
         <ymin>929</ymin>
         <ymax>1025</ymax>
      </bndbox>
   </object>
   <object>
      <name>1</name>
      <difficult>0</difficult>
      <bndbox>
         <xmin>493</xmin>
         <xmax>599</xmax>
         <ymin>923</ymin>
         <ymax>1030</ymax>
      </bndbox>
   </object>
   <object>
      <name>1</name>
      <difficult>0</difficult>
      <bndbox>
         <xmin>1782</xmin>
         <xmax>1899</xmax>
         <ymin>915</ymin>
         <ymax>1024</ymax>
      </bndbox>
   </object>
   <object>
      <name>1</name>
      <difficult>0</difficult>
      <bndbox>
         <xmin>375</xmin>
         <xmax>480</xmax>
         <ymin>903</ymin>
         <ymax>1008</ymax>
      </bndbox>
   </object>
   <object>
      <name>1</name>
      <difficult>0</difficult>
      <bndbox>
         <xmin>1429</xmin>
         <xmax>1540</xmax>
         <ymin>899</ymin>
         <ymax>1008</ymax>
      </bndbox>
   </object>
   <object>
      <name>1</name>
      <difficult>0</difficult>
      <bndbox>
         <xmin>1142</xmin>
         <xmax>1227</xmax>
         <ymin>886</ymin>
         <ymax>970</ymax>
      </bndbox>
   </object>
   <object>
      <name>1</name>
      <difficult>0</difficult>
      <bndbox>
         <xmin>952</xmin>
         <xmax>1050</xmax>
         <ymin>874</ymin>
         <ymax>975</ymax>
      </bndbox>
   </object>
   <object>
      <name>1</name>
      <difficult>0</difficult>
      <bndbox>
         <xmin>120</xmin>
         <xmax>216</xmax>
         <ymin>871</ymin>
         <ymax>977</ymax>
      </bndbox>
   </object>
   <object>
      <name>1</name>
      <difficult>0</difficult>
      <bndbox>
         <xmin>1752</xmin>
         <xmax>1850</xmax>
         <ymin>859</ymin>
         <ymax>950</ymax>
      </bndbox>
   </object>
   <object>
      <name>1</name>
      <difficult>0</difficult>
      <bndbox>
         <xmin>484</xmin>
         <xmax>584</xmax>
         <ymin>842</ymin>
         <ymax>942</ymax>
      </bndbox>
   </object>
   <object>
      <name>1</name>
      <difficult>0</difficult>
      <bndbox>
         <xmin>965</xmin>
         <xmax>1083</xmax>
         <ymin>769</ymin>
         <ymax>883</ymax>
      </bndbox>
   </object>
   <object>
      <name>1</name>
      <difficult>0</difficult>
      <bndbox>
         <xmin>93</xmin>
         <xmax>198</xmax>
         <ymin>763</ymin>
         <ymax>868</ymax>
      </bndbox>
   </object>
   <object>
      <name>1</name>
      <difficult>0</difficult>
      <bndbox>
         <xmin>1784</xmin>
         <xmax>1845</xmax>
         <ymin>735</ymin>
         <ymax>826</ymax>
      </bndbox>
   </object>
   <object>
      <name>1</name>
      <difficult>0</difficult>
      <bndbox>
         <xmin>1703</xmin>
         <xmax>1808</xmax>
         <ymin>721</ymin>
         <ymax>830</ymax>
      </bndbox>
   </object>
   <object>
      <name>1</name>
      <difficult>0</difficult>
      <bndbox>
         <xmin>731</xmin>
         <xmax>825</xmax>
         <ymin>720</ymin>
         <ymax>816</ymax>
      </bndbox>
   </object>
   <object>
      <name>1</name>
      <difficult>0</difficult>
      <bndbox>
         <xmin>625</xmin>
         <xmax>726</xmax>
         <ymin>703</ymin>
         <ymax>818</ymax>
      </bndbox>
   </object>
   <object>
      <name>1</name>
      <difficult>0</difficult>
      <bndbox>
         <xmin>1819</xmin>
         <xmax>1928</xmax>
         <ymin>687</ymin>
         <ymax>796</ymax>
      </bndbox>
   </object>
   <object>
      <name>1</name>
      <difficult>0</difficult>
      <bndbox>
         <xmin>1036</xmin>
         <xmax>1145</xmax>
         <ymin>671</ymin>
         <ymax>786</ymax>
      </bndbox>
   </object>
   <object>
      <name>1</name>
      <difficult>0</difficult>
      <bndbox>
         <xmin>1639</xmin>
         <xmax>1743</xmax>
         <ymin>670</ymin>
         <ymax>766</ymax>
      </bndbox>
   </object>
   <object>
      <name>1</name>
      <difficult>0</difficult>
      <bndbox>
         <xmin>11</xmin>
         <xmax>100</xmax>
         <ymin>646</ymin>
         <ymax>735</ymax>
      </bndbox>
   </object>
   <object>
      <name>1</name>
      <difficult>0</difficult>
      <bndbox>
         <xmin>512</xmin>
         <xmax>617</xmax>
         <ymin>632</ymin>
         <ymax>737</ymax>
      </bndbox>
   </object>
   <object>
      <name>1</name>
      <difficult>0</difficult>
      <bndbox>
         <xmin>1424</xmin>
         <xmax>1528</xmax>
         <ymin>614</ymin>
         <ymax>716</ymax>
      </bndbox>
   </object>
   <object>
      <name>1</name>
      <difficult>0</difficult>
      <bndbox>
         <xmin>1061</xmin>
         <xmax>1165</xmax>
         <ymin>559</ymin>
         <ymax>664</ymax>
      </bndbox>
   </object>
   <object>
      <name>1</name>
      <difficult>0</difficult>
      <bndbox>
         <xmin>267</xmin>
         <xmax>361</xmax>
         <ymin>548</ymin>
         <ymax>644</ymax>
      </bndbox>
   </object>
   <object>
      <name>1</name>
      <difficult>0</difficult>
      <bndbox>
         <xmin>1650</xmin>
         <xmax>1751</xmax>
         <ymin>511</ymin>
         <ymax>617</ymax>
      </bndbox>
   </object>
   <object>
      <name>1</name>
      <difficult>0</difficult>
      <bndbox>
         <xmin>1098</xmin>
         <xmax>1196</xmax>
         <ymin>486</ymin>
         <ymax>591</ymax>
      </bndbox>
   </object>
   <object>
      <name>1</name>
      <difficult>0</difficult>
      <bndbox>
         <xmin>1807</xmin>
         <xmax>1894</xmax>
         <ymin>480</ymin>
         <ymax>576</ymax>
      </bndbox>
   </object>
   <object>
      <name>1</name>
      <difficult>0</difficult>
      <bndbox>
         <xmin>1675</xmin>
         <xmax>1777</xmax>
         <ymin>450</ymin>
         <ymax>533</ymax>
      </bndbox>
   </object>
   <object>
      <name>1</name>
      <difficult>0</difficult>
      <bndbox>
         <xmin>1529</xmin>
         <xmax>1622</xmax>
         <ymin>448</ymin>
         <ymax>546</ymax>
      </bndbox>
   </object>
   <object>
      <name>1</name>
      <difficult>0</difficult>
      <bndbox>
         <xmin>93</xmin>
         <xmax>202</xmax>
         <ymin>427</ymin>
         <ymax>532</ymax>
      </bndbox>
   </object>
   <object>
      <name>1</name>
      <difficult>0</difficult>
      <bndbox>
         <xmin>1054</xmin>
         <xmax>1152</xmax>
         <ymin>360</ymin>
         <ymax>456</ymax>
      </bndbox>
   </object>
   <object>
      <name>1</name>
      <difficult>0</difficult>
      <bndbox>
         <xmin>586</xmin>
         <xmax>684</xmax>
         <ymin>348</ymin>
         <ymax>448</ymax>
      </bndbox>
   </object>
   <object>
      <name>1</name>
      <difficult>0</difficult>
      <bndbox>
         <xmin>1390</xmin>
         <xmax>1488</xmax>
         <ymin>335</ymin>
         <ymax>440</ymax>
      </bndbox>
   </object>
   <object>
      <name>1</name>
      <difficult>0</difficult>
      <bndbox>
         <xmin>133</xmin>
         <xmax>237</xmax>
         <ymin>286</ymin>
         <ymax>387</ymax>
      </bndbox>
   </object>
   <object>
      <name>1</name>
      <difficult>0</difficult>
      <bndbox>
         <xmin>1099</xmin>
         <xmax>1190</xmax>
         <ymin>267</ymin>
         <ymax>359</ymax>
      </bndbox>
   </object>
   <object>
      <name>1</name>
      <difficult>0</difficult>
      <bndbox>
         <xmin>963</xmin>
         <xmax>1065</xmax>
         <ymin>237</ymin>
         <ymax>341</ymax>
      </bndbox>
   </object>
   <object>
      <name>1</name>
      <difficult>0</difficult>
      <bndbox>
         <xmin>1539</xmin>
         <xmax>1653</xmax>
         <ymin>211</ymin>
         <ymax>308</ymax>
      </bndbox>
   </object>
   <object>
      <name>1</name>
      <difficult>0</difficult>
      <bndbox>
         <xmin>1122</xmin>
         <xmax>1222</xmax>
         <ymin>200</ymin>
         <ymax>300</ymax>
      </bndbox>
   </object>
   <object>
      <name>1</name>
      <difficult>0</difficult>
      <bndbox>
         <xmin>932</xmin>
         <xmax>1013</xmax>
         <ymin>176</ymin>
         <ymax>260</ymax>
      </bndbox>
   </object>
   <object>
      <name>1</name>
      <difficult>0</difficult>
      <bndbox>
         <xmin>462</xmin>
         <xmax>534</xmax>
         <ymin>165</ymin>
         <ymax>261</ymax>
      </bndbox>
   </object>
   <object>
      <name>1</name>
      <difficult>0</difficult>
      <bndbox>
         <xmin>510</xmin>
         <xmax>612</xmax>
         <ymin>163</ymin>
         <ymax>259</ymax>
      </bndbox>
   </object>
   <object>
      <name>1</name>
      <difficult>0</difficult>
      <bndbox>
         <xmin>675</xmin>
         <xmax>758</xmax>
         <ymin>172</ymin>
         <ymax>233</ymax>
      </bndbox>
   </object>
   <object>
      <name>1</name>
      <difficult>0</difficult>
      <bndbox>
         <xmin>777</xmin>
         <xmax>887</xmax>
         <ymin>133</ymin>
         <ymax>250</ymax>
      </bndbox>
   </object>
   <object>
      <name>1</name>
      <difficult>0</difficult>
      <bndbox>
         <xmin>1342</xmin>
         <xmax>1455</xmax>
         <ymin>130</ymin>
         <ymax>240</ymax>
      </bndbox>
   </object>
   <object>
      <name>1</name>
      <difficult>0</difficult>
      <bndbox>
         <xmin>395</xmin>
         <xmax>486</xmax>
         <ymin>115</ymin>
         <ymax>212</ymax>
      </bndbox>
   </object>
   <object>
      <name>1</name>
      <difficult>0</difficult>
      <bndbox>
         <xmin>1752</xmin>
         <xmax>1859</xmax>
         <ymin>108</ymin>
         <ymax>215</ymax>
      </bndbox>
   </object>
   <object>
      <name>1</name>
      <difficult>0</difficult>
      <bndbox>
         <xmin>190</xmin>
         <xmax>286</xmax>
         <ymin>86</ymin>
         <ymax>190</ymax>
      </bndbox>
   </object>
   <object>
      <name>1</name>
      <difficult>0</difficult>
      <bndbox>
         <xmin>508</xmin>
         <xmax>610</xmax>
         <ymin>82</ymin>
         <ymax>178</ymax>
      </bndbox>
   </object>
   <object>
      <name>1</name>
      <difficult>0</difficult>
      <bndbox>
         <xmin>665</xmin>
         <xmax>758</xmax>
         <ymin>81</ymin>
         <ymax>172</ymax>
      </bndbox>
   </object>
   <object>
      <name>1</name>
      <difficult>0</difficult>
      <bndbox>
         <xmin>1492</xmin>
         <xmax>1615</xmax>
         <ymin>29</ymin>
         <ymax>140</ymax>
      </bndbox>
   </object>
</annotation>
