<?xml version="1.0" ?>
<annotation>
   <size>
      <width>1920</width>
      <height>1080</height>
      <depth>3</depth>
   </size>
   <object>
      <name>1</name>
      <difficult>0</difficult>
      <bndbox>
         <xmin>1155</xmin>
         <xmax>1265</xmax>
         <ymin>943</ymin>
         <ymax>1054</ymax>
      </bndbox>
   </object>
   <object>
      <name>1</name>
      <difficult>0</difficult>
      <bndbox>
         <xmin>680</xmin>
         <xmax>776</xmax>
         <ymin>940</ymin>
         <ymax>1036</ymax>
      </bndbox>
   </object>
   <object>
      <name>1</name>
      <difficult>0</difficult>
      <bndbox>
         <xmin>603</xmin>
         <xmax>712</xmax>
         <ymin>843</ymin>
         <ymax>950</ymax>
      </bndbox>
   </object>
   <object>
      <name>1</name>
      <difficult>0</difficult>
      <bndbox>
         <xmin>76</xmin>
         <xmax>168</xmax>
         <ymin>835</ymin>
         <ymax>937</ymax>
      </bndbox>
   </object>
   <object>
      <name>1</name>
      <difficult>0</difficult>
      <bndbox>
         <xmin>1781</xmin>
         <xmax>1891</xmax>
         <ymin>797</ymin>
         <ymax>912</ymax>
      </bndbox>
   </object>
   <object>
      <name>1</name>
      <difficult>0</difficult>
      <bndbox>
         <xmin>456</xmin>
         <xmax>573</xmax>
         <ymin>762</ymin>
         <ymax>863</ymax>
      </bndbox>
   </object>
   <object>
      <name>1</name>
      <difficult>0</difficult>
      <bndbox>
         <xmin>379</xmin>
         <xmax>479</xmax>
         <ymin>755</ymin>
         <ymax>859</ymax>
      </bndbox>
   </object>
   <object>
      <name>1</name>
      <difficult>0</difficult>
      <bndbox>
         <xmin>1466</xmin>
         <xmax>1577</xmax>
         <ymin>748</ymin>
         <ymax>858</ymax>
      </bndbox>
   </object>
   <object>
      <name>1</name>
      <difficult>0</difficult>
      <bndbox>
         <xmin>1232</xmin>
         <xmax>1328</xmax>
         <ymin>723</ymin>
         <ymax>827</ymax>
      </bndbox>
   </object>
   <object>
      <name>1</name>
      <difficult>0</difficult>
      <bndbox>
         <xmin>1508</xmin>
         <xmax>1618</xmax>
         <ymin>679</ymin>
         <ymax>783</ymax>
      </bndbox>
   </object>
   <object>
      <name>1</name>
      <difficult>0</difficult>
      <bndbox>
         <xmin>1767</xmin>
         <xmax>1856</xmax>
         <ymin>622</ymin>
         <ymax>715</ymax>
      </bndbox>
   </object>
   <object>
      <name>1</name>
      <difficult>0</difficult>
      <bndbox>
         <xmin>167</xmin>
         <xmax>260</xmax>
         <ymin>597</ymin>
         <ymax>695</ymax>
      </bndbox>
   </object>
   <object>
      <name>1</name>
      <difficult>0</difficult>
      <bndbox>
         <xmin>966</xmin>
         <xmax>1073</xmax>
         <ymin>561</ymin>
         <ymax>663</ymax>
      </bndbox>
   </object>
   <object>
      <name>1</name>
      <difficult>0</difficult>
      <bndbox>
         <xmin>1644</xmin>
         <xmax>1745</xmax>
         <ymin>552</ymin>
         <ymax>650</ymax>
      </bndbox>
   </object>
   <object>
      <name>1</name>
      <difficult>0</difficult>
      <bndbox>
         <xmin>15</xmin>
         <xmax>115</xmax>
         <ymin>529</ymin>
         <ymax>636</ymax>
      </bndbox>
   </object>
   <object>
      <name>1</name>
      <difficult>0</difficult>
      <bndbox>
         <xmin>171</xmin>
         <xmax>278</xmax>
         <ymin>511</ymin>
         <ymax>616</ymax>
      </bndbox>
   </object>
   <object>
      <name>1</name>
      <difficult>0</difficult>
      <bndbox>
         <xmin>747</xmin>
         <xmax>851</xmax>
         <ymin>503</ymin>
         <ymax>596</ymax>
      </bndbox>
   </object>
   <object>
      <name>1</name>
      <difficult>0</difficult>
      <bndbox>
         <xmin>498</xmin>
         <xmax>603</xmax>
         <ymin>484</ymin>
         <ymax>585</ymax>
      </bndbox>
   </object>
   <object>
      <name>1</name>
      <difficult>0</difficult>
      <bndbox>
         <xmin>498</xmin>
         <xmax>616</xmax>
         <ymin>462</ymin>
         <ymax>534</ymax>
      </bndbox>
   </object>
   <object>
      <name>1</name>
      <difficult>0</difficult>
      <bndbox>
         <xmin>128</xmin>
         <xmax>222</xmax>
         <ymin>453</ymin>
         <ymax>551</ymax>
      </bndbox>
   </object>
   <object>
      <name>1</name>
      <difficult>0</difficult>
      <bndbox>
         <xmin>1689</xmin>
         <xmax>1781</xmax>
         <ymin>444</ymin>
         <ymax>536</ymax>
      </bndbox>
   </object>
   <object>
      <name>1</name>
      <difficult>0</difficult>
      <bndbox>
         <xmin>1191</xmin>
         <xmax>1293</xmax>
         <ymin>367</ymin>
         <ymax>474</ymax>
      </bndbox>
   </object>
   <object>
      <name>1</name>
      <difficult>0</difficult>
      <bndbox>
         <xmin>697</xmin>
         <xmax>780</xmax>
         <ymin>361</ymin>
         <ymax>449</ymax>
      </bndbox>
   </object>
   <object>
      <name>1</name>
      <difficult>0</difficult>
      <bndbox>
         <xmin>1735</xmin>
         <xmax>1842</xmax>
         <ymin>352</ymin>
         <ymax>449</ymax>
      </bndbox>
   </object>
   <object>
      <name>1</name>
      <difficult>0</difficult>
      <bndbox>
         <xmin>1500</xmin>
         <xmax>1600</xmax>
         <ymin>349</ymin>
         <ymax>407</ymax>
      </bndbox>
   </object>
   <object>
      <name>1</name>
      <difficult>0</difficult>
      <bndbox>
         <xmin>1405</xmin>
         <xmax>1498</xmax>
         <ymin>304</ymin>
         <ymax>402</ymax>
      </bndbox>
   </object>
   <object>
      <name>1</name>
      <difficult>0</difficult>
      <bndbox>
         <xmin>482</xmin>
         <xmax>631</xmax>
         <ymin>222</ymin>
         <ymax>301</ymax>
      </bndbox>
   </object>
   <object>
      <name>1</name>
      <difficult>0</difficult>
      <bndbox>
         <xmin>1067</xmin>
         <xmax>1173</xmax>
         <ymin>156</ymin>
         <ymax>257</ymax>
      </bndbox>
   </object>
   <object>
      <name>1</name>
      <difficult>0</difficult>
      <bndbox>
         <xmin>884</xmin>
         <xmax>986</xmax>
         <ymin>133</ymin>
         <ymax>242</ymax>
      </bndbox>
   </object>
   <object>
      <name>1</name>
      <difficult>0</difficult>
      <bndbox>
         <xmin>53</xmin>
         <xmax>145</xmax>
         <ymin>105</ymin>
         <ymax>173</ymax>
      </bndbox>
   </object>
   <object>
      <name>1</name>
      <difficult>0</difficult>
      <bndbox>
         <xmin>1470</xmin>
         <xmax>1584</xmax>
         <ymin>108</ymin>
         <ymax>225</ymax>
      </bndbox>
   </object>
   <object>
      <name>1</name>
      <difficult>0</difficult>
      <bndbox>
         <xmin>1811</xmin>
         <xmax>1920</xmax>
         <ymin>103</ymin>
         <ymax>207</ymax>
      </bndbox>
   </object>
   <object>
      <name>1</name>
      <difficult>0</difficult>
      <bndbox>
         <xmin>123</xmin>
         <xmax>220</xmax>
         <ymin>93</ymin>
         <ymax>211</ymax>
      </bndbox>
   </object>
   <object>
      <name>1</name>
      <difficult>0</difficult>
      <bndbox>
         <xmin>620</xmin>
         <xmax>718</xmax>
         <ymin>73</ymin>
         <ymax>173</ymax>
      </bndbox>
   </object>
   <object>
      <name>1</name>
      <difficult>0</difficult>
      <bndbox>
         <xmin>922</xmin>
         <xmax>993</xmax>
         <ymin>48</ymin>
         <ymax>149</ymax>
      </bndbox>
   </object>
   <object>
      <name>1</name>
      <difficult>0</difficult>
      <bndbox>
         <xmin>1330</xmin>
         <xmax>1415</xmax>
         <ymin>-2</ymin>
         <ymax>78</ymax>
      </bndbox>
   </object>
   <object>
      <name>1</name>
      <difficult>0</difficult>
      <bndbox>
         <xmin>860</xmin>
         <xmax>956</xmax>
         <ymin>-6</ymin>
         <ymax>74</ymax>
      </bndbox>
   </object>
</annotation>
